{
    "id": "DPIE_SO2",
    "maps": [
        {
            "type": "continuous",
            "entries": {
                "type": "continuous",
                "colors": [
                    "42a93cff",
                    "4aa639ff",
                    "52a436ff",
                    "5aa133ff",
                    "629e30ff",
                    "6a9c2dff",
                    "73992aff",
                    "7b9627ff",
                    "839424ff",
                    "8b9121ff",
                    "938e1eff",
                    "9b8c1bff",
                    "a38918ff",
                    "ab8715ff",
                    "b38412ff",
                    "bc810fff",
                    "c47f0cff",
                    "cc7c09ff",
                    "d47906ff",
                    "dc7703ff",
                    "e47400ff",
                    "e47800ff",
                    "e57c00ff",
                    "e68100ff",
                    "e68500ff",
                    "e68900ff",
                    "e78e00ff",
                    "e89200ff",
                    "e89600ff",
                    "e89a00ff",
                    "e99e00ff",
                    "eaa300ff",
                    "eaa700ff",
                    "eaab00ff",
                    "ebb000ff",
                    "ecb400ff",
                    "ecb800ff",
                    "ecbc00ff",
                    "edc000ff",
                    "eec500ff",
                    "eec900ff",
                    "ebbf02ff",
                    "e9b504ff",
                    "e6ab06ff",
                    "e4a108ff",
                    "e1970aff",
                    "de8d0cff",
                    "dc830eff",
                    "d97910ff",
                    "d76f12ff",
                    "d46414ff",
                    "d15a17ff",
                    "cf5019ff",
                    "cc461bff",
                    "ca3c1dff",
                    "c7321fff",
                    "c42821ff",
                    "c21e23ff",
                    "bf1425ff",
                    "bd0a27ff",
                    "ba0029ff",
                    "b7022bff",
                    "b3042cff",
                    "b0072eff",
                    "ad092fff",
                    "aa0b31ff",
                    "a60e33ff",
                    "a31034ff",
                    "a01236ff",
                    "9c1437ff",
                    "991639ff",
                    "96193bff",
                    "921b3cff",
                    "8f1d3eff",
                    "8c203fff",
                    "882241ff",
                    "852443ff",
                    "822644ff",
                    "7f2846ff",
                    "7b2b47ff",
                    "782d49ff"
                    ],
                "refs": [
                    "1",
                    "2",
                    "3",
                    "4",
                    "5",
                    "6",
                    "7",
                    "8",
                    "9",
                    "10",
                    "11",
                    "12",
                    "13",
                    "14",
                    "15",
                    "16",
                    "17",
                    "18",
                    "19",
                    "20",
                    "21",
                    "22",
                    "23",
                    "24",
                    "25",
                    "26",
                    "27",
                    "28",
                    "29",
                    "30",
                    "31",
                    "32",
                    "33",
                    "34",
                    "35",
                    "36",
                    "37",
                    "38",
                    "39",
                    "40",
                    "41",
                    "42",
                    "43",
                    "44",
                    "45",
                    "46",
                    "47",
                    "48",
                    "49",
                    "50",
                    "51",
                    "52",
                    "53",
                    "54",
                    "55",
                    "56",
                    "57",
                    "58",
                    "59",
                    "60",
                    "61",
                    "62",
                    "63",
                    "64",
                    "65",
                    "66",
                    "67",
                    "68",
                    "69",
                    "70",
                    "71",
                    "72",
                    "73",
                    "74",
                    "75",
                    "76",
                    "77",
                    "78",
                    "79",
                    "80",
                    "81"
                    ],
                "values": [
                    [0.0, 0.66],
                    [0.66, 1.33],
                    [1.33, 2.0],
                    [2.0, 2.66],
                    [2.66, 3.32],
                    [3.32, 3.99],
                    [3.99, 4.66],
                    [4.66, 5.32],
                    [5.32, 5.98],
                    [5.98, 6.65],
                    [6.65, 7.32],
                    [7.32, 7.98],
                    [7.98, 8.64],
                    [8.64, 9.31],
                    [9.31, 9.98],
                    [9.98, 10.64],
                    [10.64, 11.3],
                    [11.3, 11.97],
                    [11.97, 12.64],
                    [12.64, 13.3],
                    [13.3, 13.64],
                    [13.64, 13.97],
                    [13.97, 14.3],
                    [14.3, 14.64],
                    [14.64, 14.98],
                    [14.98, 15.31],
                    [15.31, 15.64],
                    [15.64, 15.98],
                    [15.98, 16.32],
                    [16.32, 16.65],
                    [16.65, 16.98],
                    [16.98, 17.32],
                    [17.32, 17.66],
                    [17.66, 17.99],
                    [17.99, 18.32],
                    [18.32, 18.66],
                    [18.66, 19.0],
                    [19.0, 19.33],
                    [19.33, 19.66],
                    [19.66, 20.0],
                    [20.0, 20.5],
                    [20.5, 21.0],
                    [21.0, 21.5],
                    [21.5, 22.0],
                    [22.0, 22.5],
                    [22.5, 23.0],
                    [23.0, 23.5],
                    [23.5, 24.0],
                    [24.0, 24.5],
                    [24.5, 25.0],
                    [25.0, 25.5],
                    [25.5, 26.0],
                    [26.0, 26.5],
                    [26.5, 27.0],
                    [27.0, 27.5],
                    [27.5, 28.0],
                    [28.0, 28.5],
                    [28.5, 29.0],
                    [29.0, 29.5],
                    [29.5, 30.0],
                    [30.0, 30.5],
                    [30.5, 31.0],
                    [31.0, 31.5],
                    [31.5, 32.0],
                    [32.0, 32.5],
                    [32.5, 33.0],
                    [33.0, 33.5],
                    [33.5, 34.0],
                    [34.0, 34.5],
                    [34.5, 35.0],
                    [35.0, 35.5],
                    [35.5, 36.0],
                    [36.0, 36.5],
                    [36.5, 37.0],
                    [37.0, 37.5],
                    [37.5, 38.0],
                    [38.0, 38.5],
                    [38.5, 39.0],
                    [39.0, 39.5],
                    [39.5, 40.0],
                    [40.0, 1000000.0]
                    ],
                "title": "DPIE_SO2"
            },
            "legend": {
                "colors": [
                    "42a93cff",
                    "4aa639ff",
                    "52a436ff",
                    "5aa133ff",
                    "629e30ff",
                    "6a9c2dff",
                    "73992aff",
                    "7b9627ff",
                    "839424ff",
                    "8b9121ff",
                    "938e1eff",
                    "9b8c1bff",
                    "a38918ff",
                    "ab8715ff",
                    "b38412ff",
                    "bc810fff",
                    "c47f0cff",
                    "cc7c09ff",
                    "d47906ff",
                    "dc7703ff",
                    "e47400ff",
                    "e47800ff",
                    "e57c00ff",
                    "e68100ff",
                    "e68500ff",
                    "e68900ff",
                    "e78e00ff",
                    "e89200ff",
                    "e89600ff",
                    "e89a00ff",
                    "e99e00ff",
                    "eaa300ff",
                    "eaa700ff",
                    "eaab00ff",
                    "ebb000ff",
                    "ecb400ff",
                    "ecb800ff",
                    "ecbc00ff",
                    "edc000ff",
                    "eec500ff",
                    "eec900ff",
                    "ebbf02ff",
                    "e9b504ff",
                    "e6ab06ff",
                    "e4a108ff",
                    "e1970aff",
                    "de8d0cff",
                    "dc830eff",
                    "d97910ff",
                    "d76f12ff",
                    "d46414ff",
                    "d15a17ff",
                    "cf5019ff",
                    "cc461bff",
                    "ca3c1dff",
                    "c7321fff",
                    "c42821ff",
                    "c21e23ff",
                    "bf1425ff",
                    "bd0a27ff",
                    "ba0029ff",
                    "b7022bff",
                    "b3042cff",
                    "b0072eff",
                    "ad092fff",
                    "aa0b31ff",
                    "a60e33ff",
                    "a31034ff",
                    "a01236ff",
                    "9c1437ff",
                    "991639ff",
                    "96193bff",
                    "921b3cff",
                    "8f1d3eff",
                    "8c203fff",
                    "882241ff",
                    "852443ff",
                    "822644ff",
                    "7f2846ff",
                    "7b2b47ff",
                    "782d49ff"
                    ],
                "type": "continuous",
                "tooltips": [
                    "0.0 - 0.66",
                    "0.66 - 1.33",
                    "1.33 - 2.0",
                    "2.0 - 2.66",
                    "2.66 - 3.32",
                    "3.32 - 3.99",
                    "3.99 - 4.66",
                    "4.66 - 5.32",
                    "5.32 - 5.98",
                    "5.98 - 6.65",
                    "6.65 - 7.32",
                    "7.32 - 7.98",
                    "7.98 - 8.64",
                    "8.64 - 9.31",
                    "9.31 - 9.98",
                    "9.98 - 10.64",
                    "10.64 - 11.3",
                    "11.3 - 11.97",
                    "11.97 - 12.64",
                    "12.64 - 13.3",
                    "13.3 - 13.64",
                    "13.64 - 13.97",
                    "13.97 - 14.3",
                    "14.3 - 14.64",
                    "14.64 - 14.98",
                    "14.98 - 15.31",
                    "15.31 - 15.64",
                    "15.64 - 15.98",
                    "15.98 - 16.32",
                    "16.32 - 16.65",
                    "16.65 - 16.98",
                    "16.98 - 17.32",
                    "17.32 - 17.66",
                    "17.66 - 17.99",
                    "17.99 - 18.32",
                    "18.32 - 18.66",
                    "18.66 - 19.0",
                    "19.0 - 19.33",
                    "19.33 - 19.66",
                    "19.66 - 20.0",
                    "20.0 - 20.5",
                    "20.5 - 21.0",
                    "21.0 - 21.5",
                    "21.5 - 22.0",
                    "22.0 - 22.5",
                    "22.5 - 23.0",
                    "23.0 - 23.5",
                    "23.5 - 24.0",
                    "24.0 - 24.5",
                    "24.5 - 25.0",
                    "25.0 - 25.5",
                    "25.5 - 26.0",
                    "26.0 - 26.5",
                    "26.5 - 27.0",
                    "27.0 - 27.5",
                    "27.5 - 28.0",
                    "28.0 - 28.5",
                    "28.5 - 29.0",
                    "29.0 - 29.5",
                    "29.5 - 30.0",
                    "30.0 - 30.5",
                    "30.5 - 31.0",
                    "31.0 - 31.5",
                    "31.5 - 32.0",
                    "32.0 - 32.5",
                    "32.5 - 33.0",
                    "33.0 - 33.5",
                    "33.5 - 34.0",
                    "34.0 - 34.5",
                    "34.5 - 35.0",
                    "35.0 - 35.5",
                    "35.5 - 36.0",
                    "36.0 - 36.5",
                    "36.5 - 37.0",
                    "37.0 - 37.5",
                    "37.5 - 38.0",
                    "38.0 - 38.5",
                    "38.5 - 39.0",
                    "39.0 - 39.5",
                    "39.5 - 40.0",
                    "40.0 - Inf"
                    ],
                "ticks": [
                    0.66,
                    1.33,
                    2.0,
                    2.66,
                    3.32,
                    3.99,
                    4.66,
                    5.32,
                    5.98,
                    6.65,
                    7.32,
                    7.98,
                    8.64,
                    9.31,
                    9.98,
                    10.64,
                    11.3,
                    11.97,
                    12.64,
                    13.3,
                    13.64,
                    13.97,
                    14.3,
                    14.64,
                    14.98,
                    15.31,
                    15.64,
                    15.98,
                    16.32,
                    16.65,
                    16.98,
                    17.32,
                    17.66,
                    17.99,
                    18.32,
                    18.66,
                    19.0,
                    19.33,
                    19.66,
                    20.0,
                    20.5,
                    21.0,
                    21.5,
                    22.0,
                    22.5,
                    23.0,
                    23.5,
                    24.0,
                    24.5,
                    25.0,
                    25.5,
                    26.0,
                    26.5,
                    27.0,
                    27.5,
                    28.0,
                    28.5,
                    29.0,
                    29.5,
                    30.0,
                    30.5,
                    31.0,
                    31.5,
                    32.0,
                    32.5,
                    33.0,
                    33.5,
                    34.0,
                    34.5,
                    35.0,
                    35.5,
                    36.0,
                    36.5,
                    37.0,
                    37.5,
                    38.0,
                    38.5,
                    39.0,
                    39.5,
                    40.0
                    ],
                "refs": [
                    "1",
                    "2",
                    "3",
                    "4",
                    "5",
                    "6",
                    "7",
                    "8",
                    "9",
                    "10",
                    "11",
                    "12",
                    "13",
                    "14",
                    "15",
                    "16",
                    "17",
                    "18",
                    "19",
                    "20",
                    "21",
                    "22",
                    "23",
                    "24",
                    "25",
                    "26",
                    "27",
                    "28",
                    "29",
                    "30",
                    "31",
                    "32",
                    "33",
                    "34",
                    "35",
                    "36",
                    "37",
                    "38",
                    "39",
                    "40",
                    "41",
                    "42",
                    "43",
                    "44",
                    "45",
                    "46",
                    "47",
                    "48",
                    "49",
                    "50",
                    "51",
                    "52",
                    "53",
                    "54",
                    "55",
                    "56",
                    "57",
                    "58",
                    "59",
                    "60",
                    "61",
                    "62",
                    "63",
                    "64",
                    "65",
                    "66",
                    "67",
                    "68",
                    "69",
                    "70",
                    "71",
                    "72",
                    "73",
                    "74",
                    "75",
                    "76",
                    "77",
                    "78",
                    "79",
                    "80"
                    ],
                "title": "DPIE_SO2",
                "id": "DPIE_SO2_legend",
                "minLabel": "0.0",
                "maxLabel": ">= 40.0",
                "units": "pphm"
            },
            "title": "DPIE_SO2"
        }
    ]
}